[
    {
        "name":"--ex-height",
        "syntax":"<number>",
        "initialValue":"0.32",
        "inherits":true
    },
    {
        "name":"--line",
        "syntax":"<length-percentage>",
        "initialValue":"20px",
        "inherits":true
    },
    {
        "name":"--max-width",
        "syntax":"<length-percentage>",
        "initialValue":"100%",
        "inherits":true
    },
    {
        "name":"--measure",
        "syntax":"<length>",
        "initialValue":"400px",
        "inherits":true
    },
    {
        "name":"--main-width",
        "syntax":"<length>",
        "initialValue":"500px",
        "inherits":true
    },
    {
        "name":"--min-width",
        "syntax":"<number>",
        "initialValue":"300",
        "inherits":true
    },
    {
        "name":"--width-delta",
        "syntax":"<number>",
        "initialValue":"1500",
        "inherits":true
    },
    {
        "name":"--min-font-size",
        "syntax":"<number>",
        "initialValue":"16",
        "inherits":true
    },
    {
        "name":"--max-font-size",
        "syntax":"<number>",
        "initialValue":"30",
        "inherits":true
    },
    {
        "name":"--canvas",
        "syntax":"<color>",
        "initialValue":"white",
        "inherits":true
    },
    {
        "name":"--canvas-text",
        "syntax":"<color>",
        "initialValue":"black",
        "inherits":true
    },
    {
        "name":"--gray-text",
        "syntax":"<color>",
        "initialValue":"black",
        "inherits":true
    },
    {
        "name":"--selected-item",
        "syntax":"<color>",
        "initialValue":"black",
        "inherits":true
    },
    {
        "name":"--selected-item-text",
        "syntax":"<color>",
        "initialValue":"white",
        "inherits":true
    },
    {
        "name":"--highlight",
        "syntax":"<color>",
        "initialValue":"black",
        "inherits":true
    },
    {
        "name":"--highlight-text",
        "syntax":"<color>",
        "initialValue":"white",
        "inherits":true
    },
    {
        "name":"--mark",
        "syntax":"<color>",
        "initialValue":"black",
        "inherits":true
    },
    {
        "name":"--mark-text",
        "syntax":"<color>",
        "initialValue":"white",
        "inherits":true
    },
    {
        "name":"--link-text",
        "syntax":"<color>",
        "initialValue":"black",
        "inherits":true
    },
    {
        "name":"--visited-text",
        "syntax":"<color>",
        "initialValue":"black",
        "inherits":true
    },
    {
        "name":"--active-text",
        "syntax":"<color>",
        "initialValue":"black",
        "inherits":true
    },
    {
        "name":"--accent-color",
        "syntax":"<color>",
        "initialValue":"black",
        "inherits":true
    },
    {
        "name":"--accent-color-text",
        "syntax":"<color>",
        "initialValue":"white",
        "inherits":true
    },
    {
        "name":"--button-border",
        "syntax":"<color>",
        "initialValue":"black",
        "inherits":true
    },
    {
        "name":"--button-face",
        "syntax":"<color>",
        "initialValue":"white",
        "inherits":true
    },
    {
        "name":"--button-text",
        "syntax":"<color>",
        "initialValue":"black",
        "inherits":true
    },
    {
        "name":"--field",
        "syntax":"<color>",
        "initialValue":"white",
        "inherits":true
    },
    {
        "name":"--field-text",
        "syntax":"<color>",
        "initialValue":"black",
        "inherits":true
    },
    {
        "name":"--emphasis-text",
        "syntax":"<color>",
        "initialValue":"black",
        "inherits":true
    },
    {
        "name":"--green-text",
        "syntax":"<color>",
        "initialValue":"black",
        "inherits":true
    }
]
